AUTHORS
INSTALL
LICENSE
MANIFEST.in
README
pyreb_installer.nsi
setup.py
start.py
Pyreb/PyrebApp.py
Pyreb/__init__.py
Pyreb.egg-info/PKG-INFO
Pyreb.egg-info/SOURCES.txt
Pyreb.egg-info/entry_points.txt
Pyreb.egg-info/top_level.txt
Pyreb/Controls/RegexCtrl.py
Pyreb/Controls/ResultsTree.py
Pyreb/Controls/__init__.py
Pyreb/Dialogs/AboutDialog.py
Pyreb/Dialogs/MainFrame.py
Pyreb/Dialogs/PortInputDialog.py
Pyreb/Dialogs/__init__.py
Pyreb/Resource/PreMade.list
Pyreb/Resource/README
Pyreb/Resource/pyreb_wxglade.wxg
Pyreb/Resource/pyreb_wxglade.xrc
Pyreb/Server/XMLRPCServer.py
Pyreb/Server/__init__.py
TestSuite/XMLRPCServer.py
