Metadata-Version: 1.0
Name: Pyreb
Version: 0.1.6
Summary: Pyreb is a wxPython based tool that helps building Python Regular expressions
Home-page: http://pyreb.nongnu.org/
Author: Giuseppe "Cowo" Corbelli
Author-email: cowo@lugbs.linux.it
License: GPL
Keywords: Requires,Metadata-Version
Platform: GNU/Linux
Platform: Win32
Classifier: Development Status :: 4 - Beta
Classifier: Environment :: Win32 (MS Windows)
Classifier: Environment :: X11 Applications
Classifier: Intended Audience :: Developers
Classifier: Intended Audience :: Information Technology
Classifier: License :: OSI Approved :: GNU General Public License (GPL)
Classifier: Operating System :: OS Independent
Classifier: Programming Language :: Python
Classifier: Topic :: Internet :: WWW/HTTP
Classifier: Topic :: Office/Business
Classifier: Topic :: Software Development
Classifier: Topic :: Text Processing
